camtasio/__init__.py
camtasio/_version.py
camtasio/legacy_cli.py
camtasio/project.py
camtasio/scaler.py
camtasio/annotations/__init__.py
camtasio/annotations/callouts.py
camtasio/annotations/types.py
camtasio/cli/__init__.py
camtasio/cli/app.py
camtasio/effects/__init__.py
camtasio/effects/base.py
camtasio/effects/chroma_key.py
camtasio/legacy/__init__.py
camtasio/models/__init__.py
camtasio/models/canvas.py
camtasio/models/factory.py
camtasio/models/media.py
camtasio/models/project.py
camtasio/models/source.py
camtasio/models/timeline.py
camtasio/operations/__init__.py
camtasio/operations/media_operations.py
camtasio/serialization/__init__.py
camtasio/serialization/json_encoder.py
camtasio/serialization/json_handler.py
camtasio/serialization/loader.py
camtasio/serialization/saver.py
camtasio/serialization/version.py
camtasio/transforms/__init__.py
camtasio/transforms/engine.py
camtasio/utils/__init__.py
camtasio/utils/color.py
camtasio/utils/timing.py
camtasio-2025.0.7.dist-info/METADATA
camtasio-2025.0.7.dist-info/WHEEL
camtasio-2025.0.7.dist-info/entry_points.txt
camtasio-2025.0.7.dist-info/licenses/LICENSE
camtasio-2025.0.7.dist-info/RECORD
