Metadata-Version: 2.4
Name: camtasio
Version: 2025.0.7
Summary: Python toolkit for programmatically manipulating Camtasia project files
Project-URL: Changelog, https://github.com/twardoch/camtasio/blob/main/CHANGELOG.md
Project-URL: Documentation, https://github.com/twardoch/camtasio
Project-URL: Homepage, https://github.com/twardoch/camtasio
Project-URL: Issues, https://github.com/twardoch/camtasio/issues
Project-URL: Repository, https://github.com/twardoch/camtasio
Author-email: Adam Twardoch <adam+github@twardoch.com>
Maintainer-email: Adam Twardoch <adam+github@twardoch.com>
License: MIT
License-File: LICENSE
Keywords: automation,camtasia,cmproj,editing,tscproj,video
Classifier: Development Status :: 4 - Beta
Classifier: Intended Audience :: Developers
Classifier: Intended Audience :: End Users/Desktop
Classifier: License :: OSI Approved :: MIT License
Classifier: Programming Language :: Python :: 3
Classifier: Programming Language :: Python :: 3.11
Classifier: Programming Language :: Python :: 3.12
Classifier: Programming Language :: Python :: 3.13
Classifier: Programming Language :: Python :: 3.14
Classifier: Topic :: Multimedia :: Video
Classifier: Topic :: Software Development :: Libraries :: Python Modules
Requires-Python: >=3.11
Requires-Dist: fire>=0.7.0
Requires-Dist: loguru>=0.7.3
Requires-Dist: orjson>=3.10.0
Requires-Dist: pydantic>=2.0
Requires-Dist: rich>=13.0.0
Provides-Extra: dev
Requires-Dist: build>=1.0.0; extra == 'dev'
Requires-Dist: hypothesis>=6.0.0; extra == 'dev'
Requires-Dist: mypy>=1.0; extra == 'dev'
Requires-Dist: pytest-cov>=4.1.0; extra == 'dev'
Requires-Dist: pytest>=7.4.0; extra == 'dev'
Requires-Dist: ruff>=0.1.0; extra == 'dev'
Requires-Dist: twine>=4.0.0; extra == 'dev'
